sdmxabs/__init__.py
sdmxabs/download_cache.py
sdmxabs/fetch.py
sdmxabs/fetch_gdp.py
sdmxabs/fetch_multi.py
sdmxabs/fetch_pop.py
sdmxabs/fetch_selection.py
sdmxabs/flow_metadata.py
sdmxabs/lint-all.sh
sdmxabs/measures.py
sdmxabs/py.typed
sdmxabs/xml_base.py
sdmxabs-0.2.3.dist-info/METADATA
sdmxabs-0.2.3.dist-info/WHEEL
sdmxabs-0.2.3.dist-info/licenses/LICENSE
sdmxabs-0.2.3.dist-info/RECORD
