Metadata-Version: 2.4
Name: sdmxabs
Version: 0.2.3
Summary: Download data from the Australian Bureau of Statistics (ABS) using its SDMX API
Project-URL: Repository, https://github.com/bpalmer4/sdmxabs
Project-URL: Homepage, https://github.com/bpalmer4/sdmxabs
License: LICENSE
License-File: LICENSE
Requires-Python: >=3.13
Requires-Dist: defusedxml
Requires-Dist: importlib
Requires-Dist: numpy
Requires-Dist: pandas
Requires-Dist: pathlib
Requires-Dist: requests
Requires-Dist: typing
